pycuga/__init__.py
pycuga/info.py
pycuga/printPyCuGa.py
pycuga/pycuga.py
pycuga/test.py
pycuga/algos/__init__.py
pycuga/algos/tools.py
pycuga-0.0.14.dist-info/LICENSE
pycuga-0.0.14.dist-info/METADATA
pycuga-0.0.14.dist-info/WHEEL
pycuga-0.0.14.dist-info/top_level.txt
pycuga-0.0.14.dist-info/RECORD
