Metadata-Version: 2.1
Name: pycuga
Version: 0.0.14
Summary: Python Cuda Genetic Algorithm Package
Home-page: https://github.com/issacto/PyCuGa
Author: Issac To
License: UNKNOWN
Platform: UNKNOWN
Classifier: Programming Language :: Python :: 3
Classifier: License :: OSI Approved :: MIT License
Classifier: Operating System :: OS Independent
Requires-Dist: pandas
Requires-Dist: numpy
Requires-Dist: pycuda
Requires-Dist: matplotlib
